{
  "35.552051,139.647282,2500": {
    "nearest_station": "日吉駅",
    "walk_minutes": 1
  },
  "35.507934,139.612343,2500": {
    "nearest_station": "IKEA港北 シャトルバス乗り場駅",
    "walk_minutes": 5
  },
  "35.547058,139.644054,2500": {
    "nearest_station": "プラウドシティ日吉駅",
    "walk_minutes": 4
  },
  "35.509036,139.616174,2500": {
    "nearest_station": "新横浜駅",
    "walk_minutes": 5
  },
  "35.537882,139.640247,2500": {
    "nearest_station": "長福寺前駅",
    "walk_minutes": 5
  },
  "35.545774,139.634837,2500": {
    "nearest_station": "日吉本町交番入口駅",
    "walk_minutes": 3
  },
  "35.546464,139.644732,2500": {
    "nearest_station": "プラウドシティ日吉駅",
    "walk_minutes": 2
  },
  "35.526421,139.609059,2500": {
    "nearest_station": "中井下駅",
    "walk_minutes": 4
  },
  "35.502711,139.612965,2500": {
    "nearest_station": "又口橋駅",
    "walk_minutes": 8
  },
  "35.549202,139.620435,2500": {
    "nearest_station": "高田駅",
    "walk_minutes": 1
  },
  "35.535478,139.629949,2500": {
    "nearest_station": "綱島西二丁目駅",
    "walk_minutes": 2
  },
  "35.507964,139.600842,2500": {
    "nearest_station": "小机駅",
    "walk_minutes": 2
  },
  "35.550978,139.647093,2500": {
    "nearest_station": "日吉駅",
    "walk_minutes": 3
  },
  "35.520741,139.629709,2500": {
    "nearest_station": "大倉山駅",
    "walk_minutes": 2
  },
  "35.542788,139.640758,2500": {
    "nearest_station": "綱島ＳＳＴ前駅",
    "walk_minutes": 1
  },
  "35.509617,139.600761,2500": {
    "nearest_station": "小机駅",
    "walk_minutes": 2
  },
  "35.514461,139.630833,2500": {
    "nearest_station": "菊名地区センター前駅",
    "walk_minutes": 2
  },
  "35.539698,139.642584,2500": {
    "nearest_station": "新田堀駅",
    "walk_minutes": 4
  },
  "35.510017,139.629633,2500": {
    "nearest_station": "菊名駅",
    "walk_minutes": 3
  },
  "35.498311,139.631931,2500": {
    "nearest_station": "妙蓮寺駅",
    "walk_minutes": 2
  },
  "35.496210,139.631450,2500": {
    "nearest_station": "妙蓮寺駅",
    "walk_minutes": 5
  },
  "35.528451,139.611968,2500": {
    "nearest_station": "新羽駅",
    "walk_minutes": 1
  },
  "35.495604,139.634167,2500": {
    "nearest_station": "仲手原アパート前駅",
    "walk_minutes": 5
  },
  "35.512398,139.618274,2500": {
    "nearest_station": "横浜アリーナ前駅",
    "walk_minutes": 4
  },
  "35.516693,139.623807,2500": {
    "nearest_station": "港北年金事務所入口駅",
    "walk_minutes": 3
  },
  "35.545512,139.634748,2500": {
    "nearest_station": "日吉本町交番入口駅",
    "walk_minutes": 2
  },
  "35.547726,139.638401,2500": {
    "nearest_station": "大塚製靴前駅",
    "walk_minutes": 1
  },
  "35.550454,139.626812,2500": {
    "nearest_station": "白坂駅",
    "walk_minutes": 5
  },
  "35.538890,139.632094,2500": {
    "nearest_station": "別所駅",
    "walk_minutes": 5
  },
  "35.510987,139.621338,2500": {
    "nearest_station": "横浜アリーナ前駅",
    "walk_minutes": 2
  },
  "35.518766,139.635486,2500": {
    "nearest_station": "港北区総合庁舎前駅",
    "walk_minutes": 2
  },
  "35.548476,139.619563,2500": {
    "nearest_station": "高田駅",
    "walk_minutes": 2
  },
  "35.536528,139.621422,2500": {
    "nearest_station": "町内会館前駅",
    "walk_minutes": 2
  },
  "35.520486,139.630862,2500": {
    "nearest_station": "港北区総合庁舎前駅",
    "walk_minutes": 4
  },
  "35.544488,139.626825,2500": {
    "nearest_station": "吉田口駅",
    "walk_minutes": 2
  },
  "35.547386,139.644691,2500": {
    "nearest_station": "プラウドシティ日吉駅",
    "walk_minutes": 1
  },
  "35.542967,139.632252,2500": {
    "nearest_station": "北綱島小学校入口駅",
    "walk_minutes": 5
  },
  "35.537881,139.635474,2500": {
    "nearest_station": "綱島駅入口駅",
    "walk_minutes": 4
  },
  "35.554032,139.645901,2500": {
    "nearest_station": "日吉駅",
    "walk_minutes": 5
  },
  "35.507807,139.630135,2500": {
    "nearest_station": "菊名駅",
    "walk_minutes": 6
  },
  "35.551517,139.635631,2500": {
    "nearest_station": "日吉本町駅",
    "walk_minutes": 5
  },
  "35.514064,139.620475,2500": {
    "nearest_station": "太尾新道駅",
    "walk_minutes": 2
  },
  "35.501042,139.621401,2500": {
    "nearest_station": "武相台駅",
    "walk_minutes": 9
  },
  "35.518090,139.625174,2500": {
    "nearest_station": "港北年金事務所入口駅",
    "walk_minutes": 5
  },
  "35.547417,139.621120,2500": {
    "nearest_station": "高田交差点駅",
    "walk_minutes": 4
  },
  "35.555712,139.645272,2500": {
    "nearest_station": "日吉駅通り駅",
    "walk_minutes": 1
  },
  "35.505093,139.621230,2500": {
    "nearest_station": "新横浜駅",
    "walk_minutes": 9
  },
  "35.551687,139.635929,2500": {
    "nearest_station": "日吉本町駅",
    "walk_minutes": 6
  },
  "35.545781,139.642355,2500": {
    "nearest_station": "箕輪町舟下駅",
    "walk_minutes": 3
  },
  "35.537072,139.629390,2500": {
    "nearest_station": "綱島西二丁目駅",
    "walk_minutes": 2
  },
  "35.541214,139.643755,2500": {
    "nearest_station": "新田堀駅",
    "walk_minutes": 3
  },
  "35.524644,139.632012,2500": {
    "nearest_station": "大曽根町駅",
    "walk_minutes": 3
  },
  "35.530412,139.638691,2500": {
    "nearest_station": "樽町中央駅",
    "walk_minutes": 2
  },
  "35.522742,139.625435,2500": {
    "nearest_station": "大綱中学校前駅",
    "walk_minutes": 2
  },
  "35.535688,139.624713,2500": {
    "nearest_station": "グリーンサラウンドシティ駅",
    "walk_minutes": 2
  },
  "35.541830,139.623159,2500": {
    "nearest_station": "新田中学前駅",
    "walk_minutes": 2
  },
  "35.519460,139.634174,2500": {
    "nearest_station": "港北区総合庁舎前駅",
    "walk_minutes": 3
  },
  "35.532834,139.617656,2500": {
    "nearest_station": "新吉田小学校南駅",
    "walk_minutes": 6
  },
  "35.538745,139.641364,2500": {
    "nearest_station": "新田堀駅",
    "walk_minutes": 5
  },
  "35.520755,139.622466,2500": {
    "nearest_station": "太尾南公園駅",
    "walk_minutes": 3
  },
  "35.541757,139.643270,2500": {
    "nearest_station": "綱島東四丁目駅",
    "walk_minutes": 3
  },
  "35.512087,139.631934,2500": {
    "nearest_station": "菊名地区センター前駅",
    "walk_minutes": 2
  },
  "35.556450,139.642526,2500": {
    "nearest_station": "日吉町駅",
    "walk_minutes": 1
  },
  "35.539515,139.644820,2500": {
    "nearest_station": "新田堀駅",
    "walk_minutes": 2
  },
  "35.543138,139.648361,2500": {
    "nearest_station": "日大高校正門駅",
    "walk_minutes": 3
  },
  "35.530344,139.638611,2500": {
    "nearest_station": "樽町中央駅",
    "walk_minutes": 2
  },
  "35.538117,139.642536,2500": {
    "nearest_station": "新田堀駅",
    "walk_minutes": 5
  },
  "35.535308,139.629689,2500": {
    "nearest_station": "綱島西二丁目駅",
    "walk_minutes": 3
  },
  "35.541573,139.646345,2500": {
    "nearest_station": "綱島東四丁目駅",
    "walk_minutes": 5
  },
  "35.519177,139.633916,2500": {
    "nearest_station": "港北区総合庁舎前駅",
    "walk_minutes": 2
  },
  "35.545629,139.652044,2500": {
    "nearest_station": "宮前中町駅",
    "walk_minutes": 1
  },
  "35.554939,139.615514,2500": {
    "nearest_station": "倉田屋前駅",
    "walk_minutes": 7
  },
  "35.541878,139.639176,2500": {
    "nearest_station": "綱島ＳＳＴ前駅",
    "walk_minutes": 3
  },
  "35.531361,139.633707,2500": {
    "nearest_station": "大綱橋駅",
    "walk_minutes": 2
  },
  "35.525433,139.623872,2500": {
    "nearest_station": "太尾神社前駅",
    "walk_minutes": 1
  },
  "35.526736,139.633410,2500": {
    "nearest_station": "大曽根町駅",
    "walk_minutes": 1
  },
  "35.526415,139.643773,2500": {
    "nearest_station": "表谷戸駅",
    "walk_minutes": 4
  },
  "35.531368,139.630706,2500": {
    "nearest_station": "大綱橋駅",
    "walk_minutes": 7
  },
  "35.517940,139.630837,2500": {
    "nearest_station": "大豆戸交差点駅",
    "walk_minutes": 4
  },
  "35.523032,139.625055,2500": {
    "nearest_station": "観音前駅",
    "walk_minutes": 2
  },
  "35.516163,139.630128,2500": {
    "nearest_station": "新菊名橋駅",
    "walk_minutes": 3
  },
  "35.544799,139.636096,2500": {
    "nearest_station": "日吉本町交番入口駅",
    "walk_minutes": 2
  },
  "35.513059,139.621232,2500": {
    "nearest_station": "太尾新道駅",
    "walk_minutes": 1
  },
  "35.534999,139.633612,2500": {
    "nearest_station": "綱島駅入口駅",
    "walk_minutes": 3
  },
  "35.557105,139.640885,2500": {
    "nearest_station": "日吉井田坂駅",
    "walk_minutes": 1
  },
  "35.545939,139.654825,2500": {
    "nearest_station": "一本橋駅",
    "walk_minutes": 1
  },
  "35.553038,139.613944,2500": {
    "nearest_station": "倉田屋前駅",
    "walk_minutes": 2
  },
  "35.543853,139.616144,2500": {
    "nearest_station": "四ツ家駅",
    "walk_minutes": 8
  },
  "35.530253,139.642756,2500": {
    "nearest_station": "樽町駅",
    "walk_minutes": 3
  },
  "35.513993,139.624758,2500": {
    "nearest_station": "港北車庫前駅",
    "walk_minutes": 2
  },
  "35.540043,139.615008,2500": {
    "nearest_station": "新田農協前駅",
    "walk_minutes": 1
  },
  "35.496435,139.610522,2500": {
    "nearest_station": "山王森公園前駅",
    "walk_minutes": 6
  },
  "35.546112,139.617564,2500": {
    "nearest_station": "高田駅",
    "walk_minutes": 8
  },
  "35.536421,139.637547,2500": {
    "nearest_station": "新綱島駅",
    "walk_minutes": 2
  },
  "35.546318,139.652886,2500": {
    "nearest_station": "日吉五丁目駅",
    "walk_minutes": 1
  },
  "35.522286,139.627123,2500": {
    "nearest_station": "大綱中学校前駅",
    "walk_minutes": 1
  },
  "35.512378,139.630090,2500": {
    "nearest_station": "菊名地区センター前駅",
    "walk_minutes": 4
  },
  "35.505686,139.612399,2500": {
    "nearest_station": "IKEA港北 シャトルバス乗り場駅",
    "walk_minutes": 5
  },
  "35.546627,139.631304,2500": {
    "nearest_station": "日吉本町四丁目南駅",
    "walk_minutes": 2
  },
  "35.522863,139.634666,2500": {
    "nearest_station": "熊野神社入口駅",
    "walk_minutes": 3
  },
  "35.521847,139.631729,2500": {
    "nearest_station": "熊野神社入口駅",
    "walk_minutes": 2
  },
  "35.527208,139.635311,2500": {
    "nearest_station": "大曽根町駅",
    "walk_minutes": 4
  },
  "35.523980,139.624126,2500": {
    "nearest_station": "観音前駅",
    "walk_minutes": 1
  },
  "35.554504,139.646465,2500": {
    "nearest_station": "日吉駅東口駅",
    "walk_minutes": 3
  },
  "35.550748,139.656067,2500": {
    "nearest_station": "越路駅",
    "walk_minutes": 8
  },
  "35.521349,139.631136,2500": {
    "nearest_station": "大倉山駅",
    "walk_minutes": 2
  },
  "35.512626,139.622628,2500": {
    "nearest_station": "港北車庫前駅",
    "walk_minutes": 2
  },
  "35.550120,139.620038,2500": {
    "nearest_station": "高田駅",
    "walk_minutes": 1
  },
  "35.548424,139.653465,2500": {
    "nearest_station": "日吉五丁目駅",
    "walk_minutes": 5
  },
  "35.551039,139.647321,2500": {
    "nearest_station": "日吉駅",
    "walk_minutes": 3
  },
  "35.523043,139.625087,2500": {
    "nearest_station": "観音前駅",
    "walk_minutes": 2
  },
  "35.502411,139.610667,2500": {
    "nearest_station": "又口橋駅",
    "walk_minutes": 2
  },
  "35.548249,139.628696,2500": {
    "nearest_station": "白坂東駅",
    "walk_minutes": 2
  },
  "35.525761,139.622859,2500": {
    "nearest_station": "太尾神社前駅",
    "walk_minutes": 2
  },
  "35.554695,139.646664,2500": {
    "nearest_station": "日吉駅東口駅",
    "walk_minutes": 3
  },
  "35.557977,139.626940,2500": {
    "nearest_station": "下田町駅",
    "walk_minutes": 1
  },
  "35.541230,139.641885,2500": {
    "nearest_station": "綱島ＳＳＴ脇駅",
    "walk_minutes": 2
  },
  "35.555920,139.645324,2500": {
    "nearest_station": "日吉駅通り駅",
    "walk_minutes": 1
  },
  "35.513500,139.619190,2500": {
    "nearest_station": "太尾新道駅",
    "walk_minutes": 4
  },
  "35.513320,139.632039,2500": {
    "nearest_station": "菊名地区センター前駅",
    "walk_minutes": 1
  },
  "35.534922,139.635871,2500": {
    "nearest_station": "新綱島駅",
    "walk_minutes": 2
  },
  "35.540744,139.560681,2500": {
    "nearest_station": "池田駅",
    "walk_minutes": 6
  },
  "35.537752,139.629699,2500": {
    "nearest_station": "別所駅",
    "walk_minutes": 3
  },
  "35.509731,139.635908,2500": {
    "nearest_station": "菊名小学校入口駅",
    "walk_minutes": 2
  },
  "35.539097,139.642903,2500": {
    "nearest_station": "新田堀駅",
    "walk_minutes": 4
  },
  "35.516011,139.626009,2500": {
    "nearest_station": "港北年金事務所入口駅",
    "walk_minutes": 1
  },
  "35.559084,139.630058,2500": {
    "nearest_station": "新田坂下駅",
    "walk_minutes": 1
  },
  "35.518037,139.632356,2500": {
    "nearest_station": "大豆戸交差点駅",
    "walk_minutes": 1
  },
  "35.537656,139.635307,2500": {
    "nearest_station": "綱島駅",
    "walk_minutes": 2
  },
  "35.531731,139.630744,2500": {
    "nearest_station": "大綱橋駅",
    "walk_minutes": 7
  },
  "35.505776,139.638022,2500": {
    "nearest_station": "菊名老人センター前駅",
    "walk_minutes": 1
  },
  "35.548148,139.643378,2500": {
    "nearest_station": "箕輪町駅",
    "walk_minutes": 6
  },
  "35.538206,139.630185,2500": {
    "nearest_station": "別所駅",
    "walk_minutes": 2
  },
  "35.558163,139.636417,2500": {
    "nearest_station": "下田仲町駅",
    "walk_minutes": 1
  },
  "35.552773,139.645939,2500": {
    "nearest_station": "日吉駅",
    "walk_minutes": 1
  },
  "35.549902,139.646847,2500": {
    "nearest_station": "箕輪町駅",
    "walk_minutes": 3
  },
  "35.527435,139.630613,2500": {
    "nearest_station": "大曽根町駅",
    "walk_minutes": 4
  },
  "35.538121,139.628912,2500": {
    "nearest_station": "上町［港北区］駅",
    "walk_minutes": 3
  },
  "35.503270,139.634410,2500": {
    "nearest_station": "富士塚駅",
    "walk_minutes": 3
  },
  "35.539095,139.634492,2500": {
    "nearest_station": "綱島駅",
    "walk_minutes": 4
  },
  "35.546113,139.652381,2500": {
    "nearest_station": "日吉五丁目駅",
    "walk_minutes": 1
  },
  "35.543972,139.642377,2500": {
    "nearest_station": "北綱島駅",
    "walk_minutes": 1
  },
  "35.540064,139.642183,2500": {
    "nearest_station": "新田堀駅",
    "walk_minutes": 2
  },
  "35.552473,139.632908,2500": {
    "nearest_station": "日吉本町駅",
    "walk_minutes": 7
  },
  "35.541677,139.645270,2500": {
    "nearest_station": "綱島東四丁目駅",
    "walk_minutes": 4
  },
  "35.504798,139.628973,2500": {
    "nearest_station": "富士塚駅",
    "walk_minutes": 11
  },
  "35.547115,139.639494,2500": {
    "nearest_station": "箕輪町三丁目駅",
    "walk_minutes": 2
  },
  "35.539372,139.628842,2500": {
    "nearest_station": "上町［港北区］駅",
    "walk_minutes": 1
  },
  "35.543202,139.645735,2500": {
    "nearest_station": "日大高校正門駅",
    "walk_minutes": 3
  },
  "35.521083,139.628852,2500": {
    "nearest_station": "大倉山駅",
    "walk_minutes": 2
  },
  "35.514036,139.620453,2500": {
    "nearest_station": "太尾新道駅",
    "walk_minutes": 2
  },
  "35.545727,139.643256,2500": {
    "nearest_station": "箕輪町舟下駅",
    "walk_minutes": 1
  },
  "35.522868,139.630044,2500": {
    "nearest_station": "大倉山駅",
    "walk_minutes": 1
  },
  "35.540047,139.628630,2500": {
    "nearest_station": "上町［港北区］駅",
    "walk_minutes": 1
  },
  "35.518719,139.620245,2500": {
    "nearest_station": "太尾南公園駅",
    "walk_minutes": 1
  },
  "35.549978,139.636318,2500": {
    "nearest_station": "日吉本町駅",
    "walk_minutes": 3
  },
  "35.552053,139.615994,2500": {
    "nearest_station": "高田消防前駅",
    "walk_minutes": 2
  },
  "35.535015,139.637521,2500": {
    "nearest_station": "新綱島駅",
    "walk_minutes": 3
  },
  "35.515252,139.630236,2500": {
    "nearest_station": "菊名地区センター前駅",
    "walk_minutes": 5
  },
  "35.519672,139.607501,2500": {
    "nearest_station": "専念寺前駅",
    "walk_minutes": 2
  },
  "35.507774,139.621617,2500": {
    "nearest_station": "新横浜プリンスホテル駅",
    "walk_minutes": 5
  },
  "35.525768,139.603494,2500": {
    "nearest_station": "大竹駅",
    "walk_minutes": 3
  },
  "35.498813,139.617587,2500": {
    "nearest_station": "岸根公園駅",
    "walk_minutes": 5
  }
}